datasette_insert/__init__.py
datasette_insert-0.8.dist-info/METADATA
datasette_insert-0.8.dist-info/WHEEL
datasette_insert-0.8.dist-info/entry_points.txt
datasette_insert-0.8.dist-info/top_level.txt
datasette_insert-0.8.dist-info/RECORD
