Metadata-Version: 2.1
Name: datasette-insert
Version: 0.8
Summary: Datasette plugin for inserting and updating data
Home-page: https://datasette.io/plugins/datasette-insert
Author: Simon Willison
License: Apache License, Version 2.0
Project-URL: Issues, https://github.com/simonw/datasette-insert/issues
Project-URL: CI, https://github.com/simonw/datasette-insert/actions
Project-URL: Changelog, https://github.com/simonw/datasette-insert/releases
Requires-Python: >=3.7
Requires-Dist: datasette (>=0.46)
Requires-Dist: sqlite-utils
Provides-Extra: test
Requires-Dist: pytest ; extra == 'test'
Requires-Dist: pytest-asyncio ; extra == 'test'
Requires-Dist: httpx ; extra == 'test'
Requires-Dist: datasette-auth-tokens ; extra == 'test'
